{
  "lastUpdated": "2026-06-05T04:26:06.923Z",
  "platforms": {
    "twitter": {
      "name": "X (Twitter)",
      "icon": "𝕏",
      "items": [
        {
          "rank": 1,
          "title": "#WorldEnvironmentDay",
          "url": "https://twitter.com/search?q=%23WorldEnvironmentDay",
          "hot": "",
          "platform": "twitter"
        },
        {
          "rank": 2,
          "title": "#MultibaggerChemicalStock",
          "url": "https://twitter.com/search?q=%23MultibaggerChemicalStock",
          "hot": "",
          "platform": "twitter"
        },
        {
          "rank": 3,
          "title": "#RajeshExportsNews",
          "url": "https://twitter.com/search?q=%23RajeshExportsNews",
          "hot": "",
          "platform": "twitter"
        },
        {
          "rank": 4,
          "title": "#アプリでピザハット600円",
          "url": "https://twitter.com/search?q=%23%E3%82%A2%E3%83%97%E3%83%AA%E3%81%A7%E3%83%94%E3%82%B6%E3%83%8F%E3%83%83%E3%83%88600%E5%86%86",
          "hot": "",
          "platform": "twitter"
        },
        {
          "rank": 5,
          "title": "Canes",
          "url": "https://twitter.com/search?q=Canes",
          "hot": "",
          "platform": "twitter"
        },
        {
          "rank": 6,
          "title": "#bucciovertimechallenge",
          "url": "https://twitter.com/search?q=%23bucciovertimechallenge",
          "hot": "",
          "platform": "twitter"
        },
        {
          "rank": 7,
          "title": "Melanie",
          "url": "https://twitter.com/search?q=Melanie",
          "hot": "",
          "platform": "twitter"
        },
        {
          "rank": 8,
          "title": "Seth Jarvis",
          "url": "https://twitter.com/search?q=Seth%20Jarvis",
          "hot": "",
          "platform": "twitter"
        },
        {
          "rank": 9,
          "title": "あと半日",
          "url": "https://twitter.com/search?q=%E3%81%82%E3%81%A8%E5%8D%8A%E6%97%A5",
          "hot": "",
          "platform": "twitter"
        },
        {
          "rank": 10,
          "title": "Kenzie",
          "url": "https://twitter.com/search?q=Kenzie",
          "hot": "",
          "platform": "twitter"
        },
        {
          "rank": 11,
          "title": "ドムドム",
          "url": "https://twitter.com/search?q=%E3%83%89%E3%83%A0%E3%83%89%E3%83%A0",
          "hot": "",
          "platform": "twitter"
        },
        {
          "rank": 12,
          "title": "AARON MERCURY X CH212",
          "url": "https://twitter.com/search?q=AARON%20MERCURY%20X%20CH212",
          "hot": "",
          "platform": "twitter"
        },
        {
          "rank": 13,
          "title": "Carolina",
          "url": "https://twitter.com/search?q=Carolina",
          "hot": "",
          "platform": "twitter"
        },
        {
          "rank": 14,
          "title": "McConnell",
          "url": "https://twitter.com/search?q=McConnell",
          "hot": "",
          "platform": "twitter"
        },
        {
          "rank": 15,
          "title": "Olivia Miles",
          "url": "https://twitter.com/search?q=Olivia%20Miles",
          "hot": "",
          "platform": "twitter"
        },
        {
          "rank": 16,
          "title": "Go Green",
          "url": "https://twitter.com/search?q=Go%20Green",
          "hot": "",
          "platform": "twitter"
        },
        {
          "rank": 17,
          "title": "ZUNINO AL 9009",
          "url": "https://twitter.com/search?q=ZUNINO%20AL%209009",
          "hot": "",
          "platform": "twitter"
        },
        {
          "rank": 18,
          "title": "リーリヤ",
          "url": "https://twitter.com/search?q=%E3%83%AA%E3%83%BC%E3%83%AA%E3%83%A4",
          "hot": "",
          "platform": "twitter"
        },
        {
          "rank": 19,
          "title": "Serbia",
          "url": "https://twitter.com/search?q=Serbia",
          "hot": "",
          "platform": "twitter"
        },
        {
          "rank": 20,
          "title": "Raúl Jiménez",
          "url": "https://twitter.com/search?q=Ra%C3%BAl%20Jim%C3%A9nez",
          "hot": "",
          "platform": "twitter"
        },
        {
          "rank": 21,
          "title": "アークレンジャー",
          "url": "https://twitter.com/search?q=%E3%82%A2%E3%83%BC%E3%82%AF%E3%83%AC%E3%83%B3%E3%82%B8%E3%83%A3%E3%83%BC",
          "hot": "",
          "platform": "twitter"
        },
        {
          "rank": 22,
          "title": "Torts",
          "url": "https://twitter.com/search?q=Torts",
          "hot": "",
          "platform": "twitter"
        },
        {
          "rank": 23,
          "title": "Tillis",
          "url": "https://twitter.com/search?q=Tillis",
          "hot": "",
          "platform": "twitter"
        },
        {
          "rank": 24,
          "title": "Platner",
          "url": "https://twitter.com/search?q=Platner",
          "hot": "",
          "platform": "twitter"
        },
        {
          "rank": 25,
          "title": "Collins",
          "url": "https://twitter.com/search?q=Collins",
          "hot": "",
          "platform": "twitter"
        },
        {
          "rank": 26,
          "title": "Cubs",
          "url": "https://twitter.com/search?q=Cubs",
          "hot": "",
          "platform": "twitter"
        },
        {
          "rank": 27,
          "title": "Jorge Sánchez",
          "url": "https://twitter.com/search?q=Jorge%20S%C3%A1nchez",
          "hot": "",
          "platform": "twitter"
        },
        {
          "rank": 28,
          "title": "Quiñones",
          "url": "https://twitter.com/search?q=Qui%C3%B1ones",
          "hot": "",
          "platform": "twitter"
        },
        {
          "rank": 29,
          "title": "Muncy",
          "url": "https://twitter.com/search?q=Muncy",
          "hot": "",
          "platform": "twitter"
        },
        {
          "rank": 30,
          "title": "Save Act",
          "url": "https://twitter.com/search?q=Save%20Act",
          "hot": "",
          "platform": "twitter"
        }
      ]
    },
    "bilibili": {
      "name": "Bilibili",
      "icon": "📺",
      "items": [
        {
          "rank": 1,
          "title": "不儿，你俩来真的啊？！",
          "url": "https://www.bilibili.com/video/BV1RvVo6QEqo",
          "hot": "393万播放",
          "platform": "bilibili"
        },
        {
          "rank": 2,
          "title": "回忆永远都是加分项",
          "url": "https://www.bilibili.com/video/BV1QzVR63E3L",
          "hot": "310万播放",
          "platform": "bilibili"
        },
        {
          "rank": 3,
          "title": "一顿饭只要三块钱，客人吃着吃着，人就“没了”",
          "url": "https://www.bilibili.com/video/BV15wVB6YECT",
          "hot": "165万播放",
          "platform": "bilibili"
        },
        {
          "rank": 4,
          "title": "血战到天亮，22小时挣728元1张馅饼1个茶叶蛋晚安全世界，终于可以睡觉啦",
          "url": "https://www.bilibili.com/video/BV1tMV16rEA8",
          "hot": "146万播放",
          "platform": "bilibili"
        },
        {
          "rank": 5,
          "title": "我的世界杯主题曲！IShowSpeed - World Cup (Champions)",
          "url": "https://www.bilibili.com/video/BV1jwV663EjR",
          "hot": "349万播放",
          "platform": "bilibili"
        },
        {
          "rank": 6,
          "title": "初中生斗胆跳一段jam",
          "url": "https://www.bilibili.com/video/BV1kCVU65ERM",
          "hot": "490万播放",
          "platform": "bilibili"
        },
        {
          "rank": 7,
          "title": "《你来真的啊》",
          "url": "https://www.bilibili.com/video/BV16BVy6wEfx",
          "hot": "247万播放",
          "platform": "bilibili"
        },
        {
          "rank": 8,
          "title": "《原神》洛恩角色PV——「标准化考核」",
          "url": "https://www.bilibili.com/video/BV1oqVB6BECd",
          "hot": "161万播放",
          "platform": "bilibili"
        },
        {
          "rank": 9,
          "title": "🍄欠揍气球🍄",
          "url": "https://www.bilibili.com/video/BV1W6VZ6MEbd",
          "hot": "190万播放",
          "platform": "bilibili"
        },
        {
          "rank": 10,
          "title": "【野餐】你醒啦 现在是2012年的5月份呀",
          "url": "https://www.bilibili.com/video/BV1jqVS6MECE",
          "hot": "120万播放",
          "platform": "bilibili"
        },
        {
          "rank": 11,
          "title": "“超微距”下的瑞士长什么样？",
          "url": "https://www.bilibili.com/video/BV1vkVB6NEuR",
          "hot": "248万播放",
          "platform": "bilibili"
        },
        {
          "rank": 12,
          "title": "二次元老资历童年都在听什么？！老番串烧34首大连唱！",
          "url": "https://www.bilibili.com/video/BV1B75w6zEG1",
          "hot": "144万播放",
          "platform": "bilibili"
        },
        {
          "rank": 13,
          "title": "当父母说出了正确答案：",
          "url": "https://www.bilibili.com/video/BV16kV26TES7",
          "hot": "220万播放",
          "platform": "bilibili"
        },
        {
          "rank": 14,
          "title": "特朗普的愤怒",
          "url": "https://www.bilibili.com/video/BV1XQ7Z6eEki",
          "hot": "200万播放",
          "platform": "bilibili"
        },
        {
          "rank": 15,
          "title": "初代跑男团战力排行",
          "url": "https://www.bilibili.com/video/BV1cmVz6DEmi",
          "hot": "163万播放",
          "platform": "bilibili"
        },
        {
          "rank": 16,
          "title": "兄弟们！今天给良子做一个入营测试，这身体身体素质，跟我想的不太一样啊!",
          "url": "https://www.bilibili.com/video/BV1ogV26FEhB",
          "hot": "209万播放",
          "platform": "bilibili"
        },
        {
          "rank": 17,
          "title": "下 一 个 抓 谁 ！！！",
          "url": "https://www.bilibili.com/video/BV1MG7961Efg",
          "hot": "107万播放",
          "platform": "bilibili"
        },
        {
          "rank": 18,
          "title": "今天把我关于《丧尸清道夫》的创作思路分享给大家，如果能帮到你，我会很开心。",
          "url": "https://www.bilibili.com/video/BV1xuVC6AEbg",
          "hot": "78万播放",
          "platform": "bilibili"
        },
        {
          "rank": 19,
          "title": "一辈子一定要体验一次的游戏，绝对不能被剧透的神作",
          "url": "https://www.bilibili.com/video/BV1F9Vz62ExS",
          "hot": "88万播放",
          "platform": "bilibili"
        },
        {
          "rank": 20,
          "title": "【低成本在家实现牛排自由‼️ 】",
          "url": "https://www.bilibili.com/video/BV1gzVC6kE1S",
          "hot": "72万播放",
          "platform": "bilibili"
        }
      ]
    },
    "instagram": {
      "name": "Instagram",
      "icon": "📷",
      "items": [
        {
          "rank": 1,
          "title": "#love",
          "url": "https://www.instagram.com/explore/tags/love/",
          "hot": "",
          "platform": "instagram"
        },
        {
          "rank": 2,
          "title": "#instagood",
          "url": "https://www.instagram.com/explore/tags/instagood/",
          "hot": "",
          "platform": "instagram"
        },
        {
          "rank": 3,
          "title": "#fashion",
          "url": "https://www.instagram.com/explore/tags/fashion/",
          "hot": "",
          "platform": "instagram"
        },
        {
          "rank": 4,
          "title": "#photooftheday",
          "url": "https://www.instagram.com/explore/tags/photooftheday/",
          "hot": "",
          "platform": "instagram"
        },
        {
          "rank": 5,
          "title": "#photography",
          "url": "https://www.instagram.com/explore/tags/photography/",
          "hot": "",
          "platform": "instagram"
        },
        {
          "rank": 6,
          "title": "#beautiful",
          "url": "https://www.instagram.com/explore/tags/beautiful/",
          "hot": "",
          "platform": "instagram"
        },
        {
          "rank": 7,
          "title": "#art",
          "url": "https://www.instagram.com/explore/tags/art/",
          "hot": "",
          "platform": "instagram"
        },
        {
          "rank": 8,
          "title": "#picoftheday",
          "url": "https://www.instagram.com/explore/tags/picoftheday/",
          "hot": "",
          "platform": "instagram"
        },
        {
          "rank": 9,
          "title": "#nature",
          "url": "https://www.instagram.com/explore/tags/nature/",
          "hot": "",
          "platform": "instagram"
        },
        {
          "rank": 10,
          "title": "#happy",
          "url": "https://www.instagram.com/explore/tags/happy/",
          "hot": "",
          "platform": "instagram"
        },
        {
          "rank": 11,
          "title": "#follow",
          "url": "https://www.instagram.com/explore/tags/follow/",
          "hot": "",
          "platform": "instagram"
        },
        {
          "rank": 12,
          "title": "#travel",
          "url": "https://www.instagram.com/explore/tags/travel/",
          "hot": "",
          "platform": "instagram"
        },
        {
          "rank": 13,
          "title": "#style",
          "url": "https://www.instagram.com/explore/tags/style/",
          "hot": "",
          "platform": "instagram"
        },
        {
          "rank": 14,
          "title": "#instadaily",
          "url": "https://www.instagram.com/explore/tags/instadaily/",
          "hot": "",
          "platform": "instagram"
        },
        {
          "rank": 15,
          "title": "#reels",
          "url": "https://www.instagram.com/explore/tags/reels/",
          "hot": "",
          "platform": "instagram"
        },
        {
          "rank": 16,
          "title": "#like",
          "url": "https://www.instagram.com/explore/tags/like/",
          "hot": "",
          "platform": "instagram"
        },
        {
          "rank": 17,
          "title": "#fitness",
          "url": "https://www.instagram.com/explore/tags/fitness/",
          "hot": "",
          "platform": "instagram"
        },
        {
          "rank": 18,
          "title": "#life",
          "url": "https://www.instagram.com/explore/tags/life/",
          "hot": "",
          "platform": "instagram"
        },
        {
          "rank": 19,
          "title": "#beauty",
          "url": "https://www.instagram.com/explore/tags/beauty/",
          "hot": "",
          "platform": "instagram"
        },
        {
          "rank": 20,
          "title": "#food",
          "url": "https://www.instagram.com/explore/tags/food/",
          "hot": "",
          "platform": "instagram"
        }
      ]
    },
    "zhihu": {
      "name": "知乎",
      "icon": "💡",
      "items": []
    },
    "baidu": {
      "name": "百度热搜",
      "icon": "🔍",
      "items": [
        {
          "rank": 1,
          "title": "总书记的人民情怀",
          "url": "https://www.baidu.com/s?wd=%E6%80%BB%E4%B9%A6%E8%AE%B0%E7%9A%84%E4%BA%BA%E6%B0%91%E6%83%85%E6%80%80",
          "hot": "",
          "platform": "baidu"
        },
        {
          "rank": 2,
          "title": "习近平将访问朝鲜",
          "url": "https://www.baidu.com/s?wd=%E4%B9%A0%E8%BF%91%E5%B9%B3%E5%B0%86%E8%AE%BF%E9%97%AE%E6%9C%9D%E9%B2%9C",
          "hot": "",
          "platform": "baidu"
        },
        {
          "rank": 3,
          "title": "世界杯两大夺冠热门热身赛同时翻车",
          "url": "https://www.baidu.com/s?wd=%E4%B8%96%E7%95%8C%E6%9D%AF%E4%B8%A4%E5%A4%A7%E5%A4%BA%E5%86%A0%E7%83%AD%E9%97%A8%E7%83%AD%E8%BA%AB%E8%B5%9B%E5%90%8C%E6%97%B6%E7%BF%BB%E8%BD%A6",
          "hot": "",
          "platform": "baidu"
        },
        {
          "rank": 4,
          "title": "高考安检新变化 多地提醒",
          "url": "https://www.baidu.com/s?wd=%E9%AB%98%E8%80%83%E5%AE%89%E6%A3%80%E6%96%B0%E5%8F%98%E5%8C%96%20%E5%A4%9A%E5%9C%B0%E6%8F%90%E9%86%92",
          "hot": "",
          "platform": "baidu"
        },
        {
          "rank": 5,
          "title": "日本拥核已是现实威胁",
          "url": "https://www.baidu.com/s?wd=%E6%97%A5%E6%9C%AC%E6%8B%A5%E6%A0%B8%E5%B7%B2%E6%98%AF%E7%8E%B0%E5%AE%9E%E5%A8%81%E8%83%81",
          "hot": "",
          "platform": "baidu"
        },
        {
          "rank": 6,
          "title": "高考出题人什么时候才能被“放”出来",
          "url": "https://www.baidu.com/s?wd=%E9%AB%98%E8%80%83%E5%87%BA%E9%A2%98%E4%BA%BA%E4%BB%80%E4%B9%88%E6%97%B6%E5%80%99%E6%89%8D%E8%83%BD%E8%A2%AB%E2%80%9C%E6%94%BE%E2%80%9D%E5%87%BA%E6%9D%A5",
          "hot": "",
          "platform": "baidu"
        },
        {
          "rank": 7,
          "title": "泽连斯基公开致信普京",
          "url": "https://www.baidu.com/s?wd=%E6%B3%BD%E8%BF%9E%E6%96%AF%E5%9F%BA%E5%85%AC%E5%BC%80%E8%87%B4%E4%BF%A1%E6%99%AE%E4%BA%AC",
          "hot": "",
          "platform": "baidu"
        },
        {
          "rank": 8,
          "title": "游客海上漂了7天6夜 生吃螃蟹求生",
          "url": "https://www.baidu.com/s?wd=%E6%B8%B8%E5%AE%A2%E6%B5%B7%E4%B8%8A%E6%BC%82%E4%BA%867%E5%A4%A96%E5%A4%9C%20%E7%94%9F%E5%90%83%E8%9E%83%E8%9F%B9%E6%B1%82%E7%94%9F",
          "hot": "",
          "platform": "baidu"
        },
        {
          "rank": 9,
          "title": "燃油车价格大幅跳水",
          "url": "https://www.baidu.com/s?wd=%E7%87%83%E6%B2%B9%E8%BD%A6%E4%BB%B7%E6%A0%BC%E5%A4%A7%E5%B9%85%E8%B7%B3%E6%B0%B4",
          "hot": "",
          "platform": "baidu"
        },
        {
          "rank": 10,
          "title": "追觅CEO俞浩微博被禁言",
          "url": "https://www.baidu.com/s?wd=%E8%BF%BD%E8%A7%85CEO%E4%BF%9E%E6%B5%A9%E5%BE%AE%E5%8D%9A%E8%A2%AB%E7%A6%81%E8%A8%80",
          "hot": "",
          "platform": "baidu"
        },
        {
          "rank": 11,
          "title": "中国小电驴在英国卖爆了",
          "url": "https://www.baidu.com/s?wd=%E4%B8%AD%E5%9B%BD%E5%B0%8F%E7%94%B5%E9%A9%B4%E5%9C%A8%E8%8B%B1%E5%9B%BD%E5%8D%96%E7%88%86%E4%BA%86",
          "hot": "",
          "platform": "baidu"
        },
        {
          "rank": 12,
          "title": "成都公积金单人可贷150万系谣言",
          "url": "https://www.baidu.com/s?wd=%E6%88%90%E9%83%BD%E5%85%AC%E7%A7%AF%E9%87%91%E5%8D%95%E4%BA%BA%E5%8F%AF%E8%B4%B7150%E4%B8%87%E7%B3%BB%E8%B0%A3%E8%A8%80",
          "hot": "",
          "platform": "baidu"
        },
        {
          "rank": 13,
          "title": "未成年女孩遭直播公司“围猎”",
          "url": "https://www.baidu.com/s?wd=%E6%9C%AA%E6%88%90%E5%B9%B4%E5%A5%B3%E5%AD%A9%E9%81%AD%E7%9B%B4%E6%92%AD%E5%85%AC%E5%8F%B8%E2%80%9C%E5%9B%B4%E7%8C%8E%E2%80%9D",
          "hot": "",
          "platform": "baidu"
        },
        {
          "rank": 14,
          "title": "英国间谍2次偷窃中国茶叶机密",
          "url": "https://www.baidu.com/s?wd=%E8%8B%B1%E5%9B%BD%E9%97%B4%E8%B0%8D2%E6%AC%A1%E5%81%B7%E7%AA%83%E4%B8%AD%E5%9B%BD%E8%8C%B6%E5%8F%B6%E6%9C%BA%E5%AF%86",
          "hot": "",
          "platform": "baidu"
        },
        {
          "rank": 15,
          "title": "巴西37岁女子假扮12岁女童骗收养",
          "url": "https://www.baidu.com/s?wd=%E5%B7%B4%E8%A5%BF37%E5%B2%81%E5%A5%B3%E5%AD%90%E5%81%87%E6%89%AE12%E5%B2%81%E5%A5%B3%E7%AB%A5%E9%AA%97%E6%94%B6%E5%85%BB",
          "hot": "",
          "platform": "baidu"
        },
        {
          "rank": 16,
          "title": "太阳爆发强烈耀斑 大地磁暴或将出现",
          "url": "https://www.baidu.com/s?wd=%E5%A4%AA%E9%98%B3%E7%88%86%E5%8F%91%E5%BC%BA%E7%83%88%E8%80%80%E6%96%91%20%E5%A4%A7%E5%9C%B0%E7%A3%81%E6%9A%B4%E6%88%96%E5%B0%86%E5%87%BA%E7%8E%B0",
          "hot": "",
          "platform": "baidu"
        },
        {
          "rank": 17,
          "title": "小伙练腿过度致横纹肌溶解急性肾衰竭",
          "url": "https://www.baidu.com/s?wd=%E5%B0%8F%E4%BC%99%E7%BB%83%E8%85%BF%E8%BF%87%E5%BA%A6%E8%87%B4%E6%A8%AA%E7%BA%B9%E8%82%8C%E6%BA%B6%E8%A7%A3%E6%80%A5%E6%80%A7%E8%82%BE%E8%A1%B0%E7%AB%AD",
          "hot": "",
          "platform": "baidu"
        },
        {
          "rank": 18,
          "title": "“为什么总觉得湖北一高考就下雨”",
          "url": "https://www.baidu.com/s?wd=%E2%80%9C%E4%B8%BA%E4%BB%80%E4%B9%88%E6%80%BB%E8%A7%89%E5%BE%97%E6%B9%96%E5%8C%97%E4%B8%80%E9%AB%98%E8%80%83%E5%B0%B1%E4%B8%8B%E9%9B%A8%E2%80%9D",
          "hot": "",
          "platform": "baidu"
        },
        {
          "rank": 19,
          "title": "曝美军福特号航母火灾远比描述严重",
          "url": "https://www.baidu.com/s?wd=%E6%9B%9D%E7%BE%8E%E5%86%9B%E7%A6%8F%E7%89%B9%E5%8F%B7%E8%88%AA%E6%AF%8D%E7%81%AB%E7%81%BE%E8%BF%9C%E6%AF%94%E6%8F%8F%E8%BF%B0%E4%B8%A5%E9%87%8D",
          "hot": "",
          "platform": "baidu"
        },
        {
          "rank": 20,
          "title": "杭州“短剧大女主”成“卷饼主理人”",
          "url": "https://www.baidu.com/s?wd=%E6%9D%AD%E5%B7%9E%E2%80%9C%E7%9F%AD%E5%89%A7%E5%A4%A7%E5%A5%B3%E4%B8%BB%E2%80%9D%E6%88%90%E2%80%9C%E5%8D%B7%E9%A5%BC%E4%B8%BB%E7%90%86%E4%BA%BA%E2%80%9D",
          "hot": "",
          "platform": "baidu"
        },
        {
          "rank": 21,
          "title": "实习医生无证拔牙致人死亡获刑1年半",
          "url": "https://www.baidu.com/s?wd=%E5%AE%9E%E4%B9%A0%E5%8C%BB%E7%94%9F%E6%97%A0%E8%AF%81%E6%8B%94%E7%89%99%E8%87%B4%E4%BA%BA%E6%AD%BB%E4%BA%A1%E8%8E%B7%E5%88%911%E5%B9%B4%E5%8D%8A",
          "hot": "",
          "platform": "baidu"
        },
        {
          "rank": 22,
          "title": "奚梦瑶何猷君婚礼上摆蒜苔",
          "url": "https://www.baidu.com/s?wd=%E5%A5%9A%E6%A2%A6%E7%91%B6%E4%BD%95%E7%8C%B7%E5%90%9B%E5%A9%9A%E7%A4%BC%E4%B8%8A%E6%91%86%E8%92%9C%E8%8B%94",
          "hot": "",
          "platform": "baidu"
        },
        {
          "rank": 23,
          "title": "3人P图办假证开了40多家蛋糕店",
          "url": "https://www.baidu.com/s?wd=3%E4%BA%BAP%E5%9B%BE%E5%8A%9E%E5%81%87%E8%AF%81%E5%BC%80%E4%BA%8640%E5%A4%9A%E5%AE%B6%E8%9B%8B%E7%B3%95%E5%BA%97",
          "hot": "",
          "platform": "baidu"
        },
        {
          "rank": 24,
          "title": "最后一场模拟考最后一道大题 做哭了",
          "url": "https://www.baidu.com/s?wd=%E6%9C%80%E5%90%8E%E4%B8%80%E5%9C%BA%E6%A8%A1%E6%8B%9F%E8%80%83%E6%9C%80%E5%90%8E%E4%B8%80%E9%81%93%E5%A4%A7%E9%A2%98%20%E5%81%9A%E5%93%AD%E4%BA%86",
          "hot": "",
          "platform": "baidu"
        },
        {
          "rank": 25,
          "title": "重庆动物园用活兔活鸡喂蛇引争议",
          "url": "https://www.baidu.com/s?wd=%E9%87%8D%E5%BA%86%E5%8A%A8%E7%89%A9%E5%9B%AD%E7%94%A8%E6%B4%BB%E5%85%94%E6%B4%BB%E9%B8%A1%E5%96%82%E8%9B%87%E5%BC%95%E4%BA%89%E8%AE%AE",
          "hot": "",
          "platform": "baidu"
        },
        {
          "rank": 26,
          "title": "医保个人账户跨省共济来了",
          "url": "https://www.baidu.com/s?wd=%E5%8C%BB%E4%BF%9D%E4%B8%AA%E4%BA%BA%E8%B4%A6%E6%88%B7%E8%B7%A8%E7%9C%81%E5%85%B1%E6%B5%8E%E6%9D%A5%E4%BA%86",
          "hot": "",
          "platform": "baidu"
        },
        {
          "rank": 27,
          "title": "人形机器人集体降价",
          "url": "https://www.baidu.com/s?wd=%E4%BA%BA%E5%BD%A2%E6%9C%BA%E5%99%A8%E4%BA%BA%E9%9B%86%E4%BD%93%E9%99%8D%E4%BB%B7",
          "hot": "",
          "platform": "baidu"
        },
        {
          "rank": 28,
          "title": "广东男子开迈巴赫上班失控撞墙",
          "url": "https://www.baidu.com/s?wd=%E5%B9%BF%E4%B8%9C%E7%94%B7%E5%AD%90%E5%BC%80%E8%BF%88%E5%B7%B4%E8%B5%AB%E4%B8%8A%E7%8F%AD%E5%A4%B1%E6%8E%A7%E6%92%9E%E5%A2%99",
          "hot": "",
          "platform": "baidu"
        },
        {
          "rank": 29,
          "title": "董明珠一致行动人减持格力套现超16亿",
          "url": "https://www.baidu.com/s?wd=%E8%91%A3%E6%98%8E%E7%8F%A0%E4%B8%80%E8%87%B4%E8%A1%8C%E5%8A%A8%E4%BA%BA%E5%87%8F%E6%8C%81%E6%A0%BC%E5%8A%9B%E5%A5%97%E7%8E%B0%E8%B6%8516%E4%BA%BF",
          "hot": "",
          "platform": "baidu"
        },
        {
          "rank": 30,
          "title": "美福特号航母内部画面：大面积焦黑",
          "url": "https://www.baidu.com/s?wd=%E7%BE%8E%E7%A6%8F%E7%89%B9%E5%8F%B7%E8%88%AA%E6%AF%8D%E5%86%85%E9%83%A8%E7%94%BB%E9%9D%A2%EF%BC%9A%E5%A4%A7%E9%9D%A2%E7%A7%AF%E7%84%A6%E9%BB%91",
          "hot": "",
          "platform": "baidu"
        }
      ]
    },
    "toutiao": {
      "name": "YouTube",
      "icon": "📰",
      "items": []
    }
  }
}